logbook_aiopipe/__init__.py
logbook_aiopipe-0.2.0.dist-info/METADATA
logbook_aiopipe-0.2.0.dist-info/RECORD
logbook_aiopipe-0.2.0.dist-info/WHEEL
logbook_aiopipe-0.2.0.dist-info/top_level.txt
